{"name":"P.Y.T. (Pretty Young Thing)","url":"http://www.last.fm/music/Michael+Jackson/_/P.Y.T.+(Pretty+Young+Thing)","mbid":"2138af01-2a38-4f87-acbc-ea8587079ec3","playcount":1412715,"userPlaycount":-1,"listeners":309116,"streamable":false,"id":"1149151","percentageChange":0,"tags":["pop","80s","michael jackson","funk","soul"],"wikiLastChanged":1326815590000,"wikiSummary":"&quot;P.Y.T. (Pretty Young Thing)&quot; is a song by American recording artist Michael Jackson. The original demo version of the song was written by Jackson and Greg Phillinganes. It is the sixth single from Jackson's sixth solo album, Thriller (1982). Quincy Jones passed on the song itself but liked the title and, with James Ingram, fashioned a totally new song with that title.\n  \n &quot;P.Y.T. (Pretty Young Thing)&quot; was released on September 19, 1983, as the penultimate single from Thriller.","wikiText":"&quot;P.Y.T. (Pretty Young Thing)&quot; is a song by American recording artist Michael Jackson. The original demo version of the song was written by Jackson and Greg Phillinganes. It is the sixth single from Jackson's sixth solo album, Thriller (1982). Quincy Jones passed on the song itself but liked the title and, with James Ingram, fashioned a totally new song with that title.\n  \n &quot;P.Y.T. (Pretty Young Thing)&quot; was released on September 19, 1983, as the penultimate single from Thriller. The single charted at number 10 on the Billboard Hot 100 and number 46 on the R&amp;B singles chart, becoming the sixth Top 10 hit from the album. In the UK, the song reached a peak position of 11. The single was most successful in Belgium, charting within the Top 10 at number 6. &quot;P.Y.T. (Pretty Young Thing)&quot; has been covered and sampled by numerous artists, including Monica, Justin Guarini, and Kanye West. The original demo was also remixed by The Black Eyed Peas singer will.i.am for Thriller 25.\n  \n &quot;P.Y.T. (Pretty Young Thing)&quot; was never performed live by Jackson.\n        \nUser-contributed text is available under the Creative Commons By-SA License and may also be available under the GNU FDL.","similarityMatch":0.0,"artist":"Michael Jackson","artistMbid":"210769a3-4aca-4199-a2e1-676ef376e078","album":"Thriller","albumMbid":"196971df-a7b6-3cdb-8e59-f43967cd29bf","position":8,"fullTrackAvailable":false,"nowPlaying":false,"playedWhen":null,"duration":239,"location":null}