{"name":"Rock With You","url":"http://www.last.fm/music/Michael+Jackson/_/Rock+With+You","mbid":"3772c379-f673-4c3b-a306-5efeca3a02cf","playcount":1873950,"userPlaycount":-1,"listeners":402065,"streamable":false,"id":"1023953","percentageChange":0,"tags":["pop","michael jackson","80s","disco","dance"],"wikiLastChanged":1247423564000,"wikiSummary":"&quot;Rock with You&quot; was released on November 3, 1979, as the second single from Michael Jackson's fifth solo LP and breakthrough album, Off the Wall. Written by Heatwave group member and songwriter Rod Temperton, the song helped Jackson score one of the first Billboard number-one singles in the 1980s, as well as one of the last big hits of the disco era. It reached number one on both the pop and R&amp;B singles chart and became one of Jackson's most-loved songs. A video for the song shows a smiling Jackson dancing in a sequined suit against a background laser.","wikiText":"&quot;Rock with You&quot; was released on November 3, 1979, as the second single from Michael Jackson's fifth solo LP and breakthrough album, Off the Wall. Written by Heatwave group member and songwriter Rod Temperton, the song helped Jackson score one of the first Billboard number-one singles in the 1980s, as well as one of the last big hits of the disco era. It reached number one on both the pop and R&amp;B singles chart and became one of Jackson's most-loved songs. A video for the song shows a smiling Jackson dancing in a sequined suit against a background laser. According to Billboard, the song was the fourth biggest single of 1980.\n        \nUser-contributed text is available under the Creative Commons By-SA License and may also be available under the GNU FDL.","similarityMatch":0.0,"artist":"Michael Jackson","artistMbid":"210769a3-4aca-4199-a2e1-676ef376e078","album":"Number Ones","albumMbid":"c7490fa2-f520-3c9c-a33a-24914a280e95","position":2,"fullTrackAvailable":false,"nowPlaying":false,"playedWhen":null,"duration":197,"location":null}