{"name":"The Rising Tide","url":"http://www.last.fm/music/The+Killers/_/The+Rising+Tide","mbid":"321ba78b-6f36-46ea-b7db-9d1983215440","playcount":260723,"userPlaycount":-1,"listeners":68194,"streamable":false,"id":"514952194","percentageChange":0,"tags":["indie rock","rock","10s","alternative rock","best of 2012"],"wikiLastChanged":null,"wikiSummary":null,"wikiText":null,"similarityMatch":0.0,"artist":"The Killers","artistMbid":"24b4aee8-32ed-4163-98f7-55bae67411ae","album":"Battle Born","albumMbid":"3e7ff0b1-0b4b-4737-9827-8f1a71b9fe24","position":8,"fullTrackAvailable":false,"nowPlaying":false,"playedWhen":null,"duration":257,"location":null}