{"name":"Enterlude","url":"http://www.last.fm/music/The+Killers/_/Enterlude","mbid":"6ac184da-c3ee-43f3-9569-fe2943970f39","playcount":2543671,"userPlaycount":-1,"listeners":462515,"streamable":false,"id":"66147332","percentageChange":0,"tags":["rock","indie rock","indie","alternative","alternative rock"],"wikiLastChanged":null,"wikiSummary":null,"wikiText":null,"similarityMatch":0.0,"artist":"The Killers","artistMbid":"24b4aee8-32ed-4163-98f7-55bae67411ae","album":"Sam's Town","albumMbid":"","position":2,"fullTrackAvailable":false,"nowPlaying":false,"playedWhen":null,"duration":50,"location":null}