{"name":"This Is Your Life","url":"http://www.last.fm/music/The+Killers/_/This+Is+Your+Life","mbid":"6ea9a45e-d839-4c2e-8706-ae4d9edc59aa","playcount":2077483,"userPlaycount":-1,"listeners":361416,"streamable":false,"id":"245026210","percentageChange":0,"tags":["indie","alternative","rock","indie rock","the killers"],"wikiLastChanged":null,"wikiSummary":null,"wikiText":null,"similarityMatch":0.0,"artist":"The Killers","artistMbid":"24b4aee8-32ed-4163-98f7-55bae67411ae","album":"Day & Age","albumMbid":"1bf3d6a0-b0e9-4bac-8452-f13833ab33bd","position":6,"fullTrackAvailable":false,"nowPlaying":false,"playedWhen":null,"duration":219,"location":null}