{"name":"All the Pretty Faces","url":"http://www.last.fm/music/The+Killers/_/All+the+Pretty+Faces","mbid":"a8c6b83a-28d9-4cca-9168-921aa92adfee","playcount":1610907,"userPlaycount":-1,"listeners":289943,"streamable":false,"id":"19215892","percentageChange":0,"tags":["rock","indie rock","indie","alternative","alternative rock"],"wikiLastChanged":null,"wikiSummary":null,"wikiText":null,"similarityMatch":0.0,"artist":"The Killers","artistMbid":"24b4aee8-32ed-4163-98f7-55bae67411ae","album":"Sawdust","albumMbid":"1248c1fa-741f-4e61-8c8d-57fdd046c018","position":3,"fullTrackAvailable":false,"nowPlaying":false,"playedWhen":null,"duration":287,"location":null}