{"name": "Base Ball Bear", "url": "http://www.last.fm/music/Base+Ball+Bear", "mbid": "b3b24a1d-78b4-40c9-98ef-19fb812b067a", "playcount": 2257300, "userPlaycount": -1, "listeners": 45479, "streamable": false, "id": null, "percentageChange": 0, "tags": ["j-rock", "japanese", "alternative", "rock", "indie"], "wikiLastChanged": 1280044667000, "wikiSummary": "\n                Base Ball Bear (ベースボールベアー) is a Japanese rock band from Tokyo that formally began in 2002, although the members assembled in the autumn of 2001. The band, which was initially named Planet, was formed for a one-time performance at a high school culture festival, but they decided to continue playing due to how well they were received at the festival and how much fun they were having. Base Ball Bear made its major debut in early 2006 with EMI Music Japan. Their style influences include Japanese indie rock bands Number Girl and Supercar, and British rock bands such as Oasis.\n\n        <a href=\"http://www.last.fm/music/Base+Ball+Bear\">Read more about Base Ball Bear on Last.fm</a>.\n    \n    ", "wikiText": "\n                    Base Ball Bear (ベースボールベアー) is a Japanese rock band from Tokyo that formally began in 2002, although the members assembled in the autumn of 2001. The band, which was initially named Planet, was formed for a one-time performance at a high school culture festival, but they decided to continue playing due to how well they were received at the festival and how much fun they were having. Base Ball Bear made its major debut in early 2006 with EMI Music Japan. Their style influences include Japanese indie rock bands Number Girl and Supercar, and British rock bands such as Oasis.\n\n        <a href=\"http://www.last.fm/music/Base+Ball+Bear\">Read more about Base Ball Bear on Last.fm</a>.\n    \n    \nUser-contributed text is available under the Creative Commons By-SA License and may also be available under the GNU FDL.\n    ", "similarityMatch": 0.0, "similar": [
    {
        "name": "サカナクション",
        "url": "http://www.last.fm/music/%E3%82%B5%E3%82%AB%E3%83%8A%E3%82%AF%E3%82%B7%E3%83%A7%E3%83%B3",
        "mbid": null,
        "playcount": -1,
        "userPlaycount": -1,
        "listeners": -1,
        "streamable": false,
        "id": null,
        "percentageChange": 0,
        "tags": [],
        "wikiLastChanged": null,
        "wikiSummary": null,
        "wikiText": null,
        "similarityMatch": 0.0,
        "similar": []
    },
    {
        "name": "フジファブリック",
        "url": "http://www.last.fm/music/%E3%83%95%E3%82%B8%E3%83%95%E3%82%A1%E3%83%96%E3%83%AA%E3%83%83%E3%82%AF",
        "mbid": null,
        "playcount": -1,
        "userPlaycount": -1,
        "listeners": -1,
        "streamable": false,
        "id": null,
        "percentageChange": 0,
        "tags": [],
        "wikiLastChanged": null,
        "wikiSummary": null,
        "wikiText": null,
        "similarityMatch": 0.0,
        "similar": []
    },
    {
        "name": "MONOBRIGHT",
        "url": "http://www.last.fm/music/MONOBRIGHT",
        "mbid": null,
        "playcount": -1,
        "userPlaycount": -1,
        "listeners": -1,
        "streamable": false,
        "id": null,
        "percentageChange": 0,
        "tags": [],
        "wikiLastChanged": null,
        "wikiSummary": null,
        "wikiText": null,
        "similarityMatch": 0.0,
        "similar": []
    },
    {
        "name": "ねごと",
        "url": "http://www.last.fm/music/%E3%81%AD%E3%81%94%E3%81%A8",
        "mbid": null,
        "playcount": -1,
        "userPlaycount": -1,
        "listeners": -1,
        "streamable": false,
        "id": null,
        "percentageChange": 0,
        "tags": [],
        "wikiLastChanged": null,
        "wikiSummary": null,
        "wikiText": null,
        "similarityMatch": 0.0,
        "similar": []
    },
    {
        "name": "The Telephones",
        "url": "http://www.last.fm/music/The+Telephones",
        "mbid": null,
        "playcount": -1,
        "userPlaycount": -1,
        "listeners": -1,
        "streamable": false,
        "id": null,
        "percentageChange": 0,
        "tags": [],
        "wikiLastChanged": null,
        "wikiSummary": null,
        "wikiText": null,
        "similarityMatch": 0.0,
        "similar": []
    }
]}