{"name": "Moi dix Mois", "url": "http://www.last.fm/music/Moi+dix+Mois", "mbid": "935d146a-ab8a-4745-b4c4-6043d4cc15c4", "playcount": 4182100, "userPlaycount": -1, "listeners": 94355, "streamable": true, "id": null, "percentageChange": 0, "tags": ["visual kei", "j-rock", "japanese", "gothic", "gothic metal"], "wikiLastChanged": 1352552381000, "wikiSummary": "\n                Moi dix Mois is the solo project of <a href=\"http://www.last.fm/music/Mana\" class=\"bbcode_artist\">Mana</a>, formerly the leader and guitarist of the influential Japanese <a href=\"http://www.last.fm/tag/visual%20kei\" class=\"bbcode_tag\" rel=\"tag\">visual kei</a> band <a href=\"http://www.last.fm/music/MALICE+MIZER\" class=\"bbcode_artist\">MALICE MIZER</a>. He started the band in Tokyo, Japan in 2002, three months after MALICE MIZER went on hiatus. The current lineup consists of Mana (guitar, synths, programming), project support members: K (guitar and backing vocals), Seth (lead vocals), Sugiya (bass), and Hayato (drums).   \n\n        <a href=\"http://www.last.fm/music/Moi+dix+Mois\">Read more about Moi dix Mois on Last.fm</a>.\n    \n    ", "wikiText": "\n                    Moi dix Mois is the solo project of <a href=\"http://www.last.fm/music/Mana\" class=\"bbcode_artist\">Mana</a>, formerly the leader and guitarist of the influential Japanese <a href=\"http://www.last.fm/tag/visual%20kei\" class=\"bbcode_tag\" rel=\"tag\">visual kei</a> band <a href=\"http://www.last.fm/music/MALICE+MIZER\" class=\"bbcode_artist\">MALICE MIZER</a>. He started the band in Tokyo, Japan in 2002, three months after MALICE MIZER went on hiatus. The current lineup consists of Mana (guitar, synths, programming), project support members: K (guitar and backing vocals), Seth (lead vocals), Sugiya (bass), and Hayato (drums).   \n\n        <a href=\"http://www.last.fm/music/Moi+dix+Mois\">Read more about Moi dix Mois on Last.fm</a>.\n    \n    \nUser-contributed text is available under the Creative Commons By-SA License and may also be available under the GNU FDL.\n    ", "similarityMatch": 0.0, "similar": [
    {
        "name": "MALICE MIZER",
        "url": "http://www.last.fm/music/MALICE+MIZER",
        "mbid": null,
        "playcount": -1,
        "userPlaycount": -1,
        "listeners": -1,
        "streamable": false,
        "id": null,
        "percentageChange": 0,
        "tags": [],
        "wikiLastChanged": null,
        "wikiSummary": null,
        "wikiText": null,
        "similarityMatch": 0.0,
        "similar": []
    },
    {
        "name": "Art Cube",
        "url": "http://www.last.fm/music/Art+Cube",
        "mbid": null,
        "playcount": -1,
        "userPlaycount": -1,
        "listeners": -1,
        "streamable": false,
        "id": null,
        "percentageChange": 0,
        "tags": [],
        "wikiLastChanged": null,
        "wikiSummary": null,
        "wikiText": null,
        "similarityMatch": 0.0,
        "similar": []
    },
    {
        "name": "Kaya",
        "url": "http://www.last.fm/music/Kaya",
        "mbid": null,
        "playcount": -1,
        "userPlaycount": -1,
        "listeners": -1,
        "streamable": false,
        "id": null,
        "percentageChange": 0,
        "tags": [],
        "wikiLastChanged": null,
        "wikiSummary": null,
        "wikiText": null,
        "similarityMatch": 0.0,
        "similar": []
    },
    {
        "name": "HIZAKI grace project",
        "url": "http://www.last.fm/music/HIZAKI+grace+project",
        "mbid": null,
        "playcount": -1,
        "userPlaycount": -1,
        "listeners": -1,
        "streamable": false,
        "id": null,
        "percentageChange": 0,
        "tags": [],
        "wikiLastChanged": null,
        "wikiSummary": null,
        "wikiText": null,
        "similarityMatch": 0.0,
        "similar": []
    },
    {
        "name": "Versailles",
        "url": "http://www.last.fm/music/Versailles",
        "mbid": null,
        "playcount": -1,
        "userPlaycount": -1,
        "listeners": -1,
        "streamable": false,
        "id": null,
        "percentageChange": 0,
        "tags": [],
        "wikiLastChanged": null,
        "wikiSummary": null,
        "wikiText": null,
        "similarityMatch": 0.0,
        "similar": []
    }
]}