{"name":"Ize of the World","url":"http://www.last.fm/music/The+Strokes/_/Ize+of+the+World","mbid":"1b6e7232-a61c-4c29-81a2-21c173d71383","playcount":1632635,"userPlaycount":-1,"listeners":284561,"streamable":false,"id":"31242801","percentageChange":0,"tags":["indie rock","rock","indie","alternative rock","garage rock"],"wikiLastChanged":null,"wikiSummary":null,"wikiText":null,"similarityMatch":0.0,"artist":"The Strokes","artistMbid":"f181961b-20f7-459e-89de-920ef03c7ed0","album":"First Impressions of Earth","albumMbid":"04d947c3-83c8-3d12-96cd-802c64aea532","position":12,"fullTrackAvailable":false,"nowPlaying":false,"playedWhen":null,"duration":265,"location":null}