{"name":"The Way It Is","url":"http://www.last.fm/music/The+Strokes/_/The+Way+It+Is","mbid":"6d5271da-6e99-4a70-9e54-710657d01602","playcount":1732134,"userPlaycount":-1,"listeners":393875,"streamable":false,"id":"2795828","percentageChange":0,"tags":["indie rock","rock","indie","alternative rock","garage rock"],"wikiLastChanged":null,"wikiSummary":null,"wikiText":null,"similarityMatch":0.0,"artist":"The Strokes","artistMbid":"f181961b-20f7-459e-89de-920ef03c7ed0","album":"Room on Fire","albumMbid":"42e1696c-1b28-33ee-9289-ab6fc879d28e","position":9,"fullTrackAvailable":false,"nowPlaying":false,"playedWhen":null,"duration":82,"location":null}