{"name":"North","url":"http://www.last.fm/music/Phoenix/_/North","mbid":"7aec1d49-2aa4-4c7c-8675-f07b9c131364","playcount":589654,"userPlaycount":-1,"listeners":121328,"streamable":false,"id":"45877591","percentageChange":0,"tags":["instrumental","indie","mellow","indie rock","french"],"wikiLastChanged":null,"wikiSummary":null,"wikiText":null,"similarityMatch":0.0,"artist":"Phoenix","artistMbid":"02f4c1ff-65e0-4412-8e8b-6239b0faecb5","album":"It's Never Been Like That","albumMbid":"1fc38ee3-2d1b-3298-978c-35bdeb39bff1","position":8,"fullTrackAvailable":false,"nowPlaying":false,"playedWhen":null,"duration":302,"location":null}