{"name":"Dark Messages","url":"http://www.last.fm/music/Air/_/Dark+Messages","mbid":"544fb8e3-909c-49fa-ac32-ed1ab7f9ce32","playcount":618900,"userPlaycount":-1,"listeners":173465,"streamable":false,"id":"12463","percentageChange":0,"tags":["electronic","chillout","electronica","ambient","soundtrackgdchill"],"wikiLastChanged":null,"wikiSummary":null,"wikiText":null,"similarityMatch":0.0,"artist":"Air","artistMbid":"018dcc90-b1a2-400a-a96e-64b6a101f009","album":"The Virgin Suicides","albumMbid":"0cfa9e94-3360-30b3-acc8-d3d1db979756","position":5,"fullTrackAvailable":false,"nowPlaying":false,"playedWhen":null,"duration":147,"location":null}