{"name":"Why Don't You Get a Job?","url":"http://www.last.fm/music/The+Offspring/_/Why+Don%27t+You+Get+a+Job%3F","mbid":"13a72fc3-1bd2-46c2-ad6e-27fc541729f9","playcount":2082303,"userPlaycount":-1,"listeners":439903,"streamable":false,"id":"1008946","percentageChange":0,"tags":["punk rock","rock","punk","alternative rock","the offspring"],"wikiLastChanged":1286993305000,"wikiSummary":"&quot;Why Don't You Get a Job?&quot; is a ska/punk rock song by The Offspring. The song is featured as the 11th track on The Offspring's fifth studio album Americana (1998) and was released as the second single from the album. The song also appears as the seventh track on the band's Greatest Hits album (2005). The main tune of the song is inspired by The Beatles' song &quot;Ob-La-Di, Ob-La-Da&quot;.","wikiText":"&quot;Why Don't You Get a Job?&quot; is a ska/punk rock song by The Offspring. The song is featured as the 11th track on The Offspring's fifth studio album Americana (1998) and was released as the second single from the album. The song also appears as the seventh track on the band's Greatest Hits album (2005). The main tune of the song is inspired by The Beatles' song &quot;Ob-La-Di, Ob-La-Da&quot;.\n        \nUser-contributed text is available under the Creative Commons By-SA License and may also be available under the GNU FDL.","similarityMatch":0.0,"artist":"The Offspring","artistMbid":"23a03e33-a603-404e-bcbf-2c00159d7067","album":"Americana","albumMbid":"f9be3361-c1e1-48e1-8167-f19a54f719f2","position":11,"fullTrackAvailable":false,"nowPlaying":false,"playedWhen":null,"duration":173,"location":null}