{"name":"Bad News","url":"http://www.last.fm/music/Kanye+West/_/Bad+News","mbid":"1818fc80-7c01-4dda-89e1-a24851ad1838","playcount":885623,"userPlaycount":-1,"listeners":214027,"streamable":false,"id":"239647429","percentageChange":0,"tags":["kanye west","hip-hop","hip hop","rnb","pop"],"wikiLastChanged":1254234326000,"wikiSummary":"Kanye uses the sample See-Line Woman from Nina Simone's Feeling Good album. ","wikiText":"Kanye uses the sample See-Line Woman from Nina Simone's Feeling Good album. \n        \nUser-contributed text is available under the Creative Commons By-SA License and may also be available under the GNU FDL.","similarityMatch":0.0,"artist":"Kanye West","artistMbid":"164f0d73-1234-4e2c-8743-d77bf2191051","album":"808s & Heartbreak","albumMbid":"2e817d2f-34a3-3e6a-97e9-376453421fea","position":9,"fullTrackAvailable":false,"nowPlaying":false,"playedWhen":null,"duration":239,"location":null}