{"name":"The Huts","url":"http://www.last.fm/music/Mogwai/_/The+Huts","mbid":"308ce26e-b938-4564-8779-acbcd77e6fbe","playcount":24190,"userPlaycount":-1,"listeners":9173,"streamable":false,"id":"627134009","percentageChange":0,"tags":["new"],"wikiLastChanged":null,"wikiSummary":null,"wikiText":null,"similarityMatch":0.0,"artist":"Mogwai","artistMbid":"cee3f961-4197-483b-a3ad-73242a97eb4a","album":"Les Revenants","albumMbid":"a98f8be9-89a2-4039-b118-491cf690ea4a","position":3,"fullTrackAvailable":false,"nowPlaying":false,"playedWhen":null,"duration":209,"location":null}