{"name":"Kids Will Be Skeletons","url":"http://www.last.fm/music/Mogwai/_/Kids+Will+Be+Skeletons","mbid":"32a71390-e88a-454f-a8dd-ac9162ea32f4","playcount":787798,"userPlaycount":-1,"listeners":144734,"streamable":false,"id":"1613837","percentageChange":0,"tags":["post-rock","instrumental","ambient","post rock","chillout"],"wikiLastChanged":null,"wikiSummary":null,"wikiText":null,"similarityMatch":0.0,"artist":"Mogwai","artistMbid":"cee3f961-4197-483b-a3ad-73242a97eb4a","album":"Happy Songs for Happy People","albumMbid":"7417ef96-c8fd-45f5-a6f4-432751542af4","position":3,"fullTrackAvailable":false,"nowPlaying":false,"playedWhen":null,"duration":327,"location":null}