{"id":3462786,"title":"Joe Bonamassa & Beth Hart","artists":["Joe Bonamassa & Beth Hart"],"headliner":"Joe Bonamassa & Beth Hart","startDate":1372237141000,"endDate":null,"description":"","url":"http://www.last.fm/event/3462786+Joe+Bonamassa+-+Beth+Hart+at+Lotto+Arena+on+26+June+2013","website":"","attendance":4,"reviews":0,"venue":{"name":"Lotto Arena","url":"http://www.last.fm/venue/8800944+Lotto+Arena","website":"http://www.lotto-arena.be","city":"Antwerpen","country":"Belgium","street":"Schijnpoortweg 119","postal":"2170","phonenumber":"03 400 60 00","latitude":51.231728,"longitude":4.440409,"timezone":null,"id":"8800944"},"ticketSuppliers":[],"attendanceStatus":null}