{"name":"Been Down So Long","url":"http://www.last.fm/music/The+Doors/_/Been+Down+So+Long","mbid":"707cf9a9-9b5d-4601-bbb7-7b0dd95bc9e7","playcount":689587,"userPlaycount":-1,"listeners":177070,"streamable":true,"id":"2723419","percentageChange":0,"tags":["classic rock","blues rock","rock","blues","the doors"],"wikiLastChanged":1232534777000,"wikiSummary":"Been Down So Long is a reference to Richard Farina's novel Been Down So Long That It Looks Like Up To Me (1966) in which the strange college student Gnossos Pappadopoulis encounters everything that makes the sixties the 60s.","wikiText":"Been Down So Long is a reference to Richard Farina's novel Been Down So Long That It Looks Like Up To Me (1966) in which the strange college student Gnossos Pappadopoulis encounters everything that makes the sixties the 60s.\n        \nUser-contributed text is available under the Creative Commons By-SA License and may also be available under the GNU FDL.","similarityMatch":0.0,"artist":"The Doors","artistMbid":"9efff43b-3b29-4082-824e-bc82f646f93d","album":"L.A. Woman","albumMbid":"c1c273c3-1299-4352-a581-89971f3e4d80","position":3,"fullTrackAvailable":false,"nowPlaying":false,"playedWhen":null,"duration":275,"location":null}