{"name":"Das finde ich gut","url":"http://www.last.fm/music/Die+%C3%84rzte/_/Das+finde+ich+gut","mbid":"dd45d8ee-41ba-4d8a-a8f5-48ddfebbb39e","playcount":41447,"userPlaycount":-1,"listeners":7236,"streamable":false,"id":"578299407","percentageChange":0,"tags":["rock","punk","german","punk rock","deutsch"],"wikiLastChanged":null,"wikiSummary":null,"wikiText":null,"similarityMatch":0.0,"artist":"Die Ärzte","artistMbid":"f2fb0ff0-5679-42ec-a55c-15109ce6e320","album":"auch","albumMbid":"d020e304-ea9a-4395-920e-62b740e3f7f6","position":13,"fullTrackAvailable":false,"nowPlaying":false,"playedWhen":null,"duration":156,"location":null}