{"name":"Lazy Eye (Jason Bentley Remix)","url":"http://www.last.fm/music/Silversun+Pickups/_/Lazy+Eye+(Jason+Bentley+Remix)","mbid":"9b9f72b1-288d-4106-bf19-54e1ef5d9d6a","playcount":4408,"userPlaycount":-1,"listeners":1660,"streamable":false,"id":null,"percentageChange":0,"tags":[],"wikiLastChanged":null,"wikiSummary":null,"wikiText":null,"similarityMatch":0.0,"artist":"Silversun Pickups","artistMbid":"b5bd9f88-962e-4730-84a7-795592ba42e8","album":null,"albumMbid":null,"position":-1,"fullTrackAvailable":false,"nowPlaying":false,"playedWhen":null,"duration":346,"location":null}