{"name":"Helix (Extended)","url":"http://www.last.fm/music/Justice/_/Helix+(Extended)","mbid":"11db0ea5-7cef-4cb3-a85d-1a7d1fe70a5f","playcount":9059,"userPlaycount":-1,"listeners":3711,"streamable":false,"id":"627110379","percentageChange":0,"tags":[],"wikiLastChanged":null,"wikiSummary":null,"wikiText":null,"similarityMatch":0.0,"artist":"Justice","artistMbid":"444f2191-8841-440e-bbc1-6fd564893946","album":"Helix","albumMbid":"feabab88-218a-4a61-8fce-815ebd0709ef","position":1,"fullTrackAvailable":false,"nowPlaying":false,"playedWhen":null,"duration":358,"location":null}