{"name":"SRXT","url":"http://www.last.fm/music/Bloc+Party/_/SRXT","mbid":"1613d696-7a88-4898-8946-693ff3c73b74","playcount":1140019,"userPlaycount":-1,"listeners":239538,"streamable":false,"id":"75663386","percentageChange":0,"tags":["indie","indie rock","alternative","rock","british"],"wikiLastChanged":null,"wikiSummary":null,"wikiText":null,"similarityMatch":0.0,"artist":"Bloc Party","artistMbid":"8c538f11-c141-4588-8ecb-931083524186","album":"A Weekend In The City","albumMbid":"00ef5e74-6546-4da4-8432-eb375e40b0e0","position":12,"fullTrackAvailable":false,"nowPlaying":false,"playedWhen":null,"duration":291,"location":null}