{"name":"Rosenrot","url":"http://www.last.fm/music/Rammstein/_/Rosenrot","mbid":"89447a3b-d5ee-4b5a-b03e-2b2b3b76dd28","playcount":2171163,"userPlaycount":-1,"listeners":261776,"streamable":false,"id":"28158294","percentageChange":0,"tags":["industrial metal","metal","industrial","german","rammstein"],"wikiLastChanged":null,"wikiSummary":null,"wikiText":null,"similarityMatch":0.0,"artist":"Rammstein","artistMbid":"b2d122f9-eadb-4930-a196-8f221eeb0c66","album":"Rosenrot","albumMbid":"f3bfed3d-c1d2-3599-b6d7-3916be6c53dc","position":3,"fullTrackAvailable":false,"nowPlaying":false,"playedWhen":null,"duration":234,"location":null}