{"name":"Amerika","url":"http://www.last.fm/music/Rammstein/_/Amerika","mbid":"e7395733-49c9-4031-a168-92929a6168a4","playcount":2883791,"userPlaycount":-1,"listeners":386333,"streamable":false,"id":"12342902","percentageChange":0,"tags":["industrial metal","metal","german","industrial","rock"],"wikiLastChanged":1239215224000,"wikiSummary":"The song deals with the worldwide dominance of the culture of the United States of America. It is sung largely in German with a chorus partly in English. It has received mixed reviews: some perceive it as anti-American, others as being opposed to globalization. The band views it as a satirical commentary on Cocacolonization. It features mentions of Coca-Cola, Wonderbra, and Mickey Mouse.","wikiText":"The song deals with the worldwide dominance of the culture of the United States of America. It is sung largely in German with a chorus partly in English. It has received mixed reviews: some perceive it as anti-American, others as being opposed to globalization. The band views it as a satirical commentary on Cocacolonization. It features mentions of Coca-Cola, Wonderbra, and Mickey Mouse.\n        \nUser-contributed text is available under the Creative Commons By-SA License and may also be available under the GNU FDL.","similarityMatch":0.0,"artist":"Rammstein","artistMbid":"b2d122f9-eadb-4930-a196-8f221eeb0c66","album":"Reise Reise","albumMbid":"","position":6,"fullTrackAvailable":false,"nowPlaying":false,"playedWhen":null,"duration":226,"location":null}