{"name":"Been A Son","url":"http://www.last.fm/music/Nirvana/_/Been+A+Son","mbid":"9c75c8a1-c08d-47af-85e6-610cfdf72c23","playcount":1767264,"userPlaycount":-1,"listeners":368573,"streamable":false,"id":"1005604","percentageChange":0,"tags":["grunge","rock","90s","alternative","nirvana"],"wikiLastChanged":null,"wikiSummary":null,"wikiText":null,"similarityMatch":0.0,"artist":"Nirvana","artistMbid":"5b11f4ce-a62d-471e-81fc-a69a8278c7da","album":"Incesticide","albumMbid":"9ca75816-f988-4ea9-9921-c9efa97a58da","position":4,"fullTrackAvailable":false,"nowPlaying":false,"playedWhen":null,"duration":154,"location":null}