{"id":3486193,"title":"Bollywood Showstoppers 2013","artists":["Atif Aslam","Shaan","Bipasha Basu","Malaika Arora Khan","Bolly Flex"],"headliner":"Atif Aslam","startDate":1365352200000,"endDate":null,"description":"<div class=\"bbcode\">Flex FX returns in spectacular fashion with a new musical dance extravaganza to bring you Bollywood like you’ve never seen it before with Bollywood Showstoppers at The O2 on Sunday 7 April 2013.<br /><br />The Bollywood Showstoppers include the beautiful Bollywood icon BIPASHA BASU, the dancing queen MALAIKA ARORA KHAN, the sensational SHAAN and the rockstar ATIF ASLAM. All performing live and exclusive and supported by the UK’s most popular Bollywood dancers BOLLY FLEX. For more information visit <a href=\"http://www.bollywoodshowstoppers.com\" rel=\"nofollow\">www.bollywoodshowstoppers.com</a><br /><br /><a href=\"http://www.last.fm/music/Atif+Aslam\" class=\"bbcode_artist\">Atif Aslam</a> <a href=\"http://www.last.fm/music/Bipasha+Basu\" class=\"bbcode_artist\">Bipasha Basu</a> <a href=\"http://www.last.fm/music/Malaika+Arora+Khan\" class=\"bbcode_artist\">Malaika Arora Khan</a> <a href=\"http://www.last.fm/music/Shaan\" class=\"bbcode_artist\">Shaan</a> [event=]Official Website[/event] <a href=\"http://www.last.fm/tag/naz%20choudhury\" class=\"bbcode_tag\" rel=\"tag\">naz choudhury</a><span title=\"Unknown label\" class=\"bbcode_unknown\">Flex FX</span></div>","url":"http://www.last.fm/event/3486193+Bollywood+Showstoppers+2013","website":"http://www.theo2.co.uk/event/bollywood-showstoppers-20130407.html","attendance":3,"reviews":0,"venue":{"name":"O2 Arena","url":"http://www.last.fm/venue/8783707+O2+Arena","website":"http://www.theo2.co.uk","city":"London","country":"United Kingdom","street":"Peninsula Square","postal":"SE10 0DX","phonenumber":"Tickets: 0161 385 3211, Venue: 020 8463 2000","latitude":51.487583,"longitude":0.006877,"timezone":null,"id":"8783707"},"ticketSuppliers":[],"attendanceStatus":null}