{"name":"Dangerous Animals","url":"http://www.last.fm/music/Arctic+Monkeys/_/Dangerous+Animals","mbid":"bdf0d702-cb3d-4d21-8263-0382c1251e91","playcount":1911511,"userPlaycount":-1,"listeners":239825,"streamable":false,"id":"264094458","percentageChange":0,"tags":["indie rock","indie","rock","alternative rock","british"],"wikiLastChanged":null,"wikiSummary":null,"wikiText":null,"similarityMatch":0.0,"artist":"Arctic Monkeys","artistMbid":"ada7a83c-e3e1-40f1-93f9-3e73dbc9298a","album":"Humbug","albumMbid":"053ee18e-0c83-4f73-976e-d36746937d64","position":3,"fullTrackAvailable":false,"nowPlaying":false,"playedWhen":null,"duration":210,"location":null}